yeagerai/__init__.py
yeagerai/agent/__init__.py
yeagerai/agent/master_template.py
yeagerai/agent/output_parser.py
yeagerai/agent/prompt_template.py
yeagerai/agent/yeagerai_agent.py
yeagerai/interfaces/__init__.py
yeagerai/interfaces/cli.py
yeagerai/interfaces/gradio_chat.py
yeagerai/interfaces/callbacks/__init__.py
yeagerai/interfaces/callbacks/local_file_system_n_git.py
yeagerai/memory/__init__.py
yeagerai/memory/yeagerai_context.py
yeagerai/memory/callbacks/__init__.py
yeagerai/memory/callbacks/session_memory_handler.py
yeagerai/toolkit/__init__.py
yeagerai/toolkit/yeagerai_tool.py
yeagerai/toolkit/yeagerai_toolkit.py
yeagerai/toolkit/create_tool_mocked_tests/__init__.py
yeagerai/toolkit/create_tool_mocked_tests/create_tool_mocked_tests.py
yeagerai/toolkit/create_tool_mocked_tests/create_tool_mocked_tests_master_prompt.py
yeagerai/toolkit/create_tool_source/__init__.py
yeagerai/toolkit/create_tool_source/create_tool_master_prompt.py
yeagerai/toolkit/create_tool_source/create_tool_source.py
yeagerai/toolkit/design_solution_sketch/__init__.py
yeagerai/toolkit/design_solution_sketch/design_solution_sketch.py
yeagerai/toolkit/design_solution_sketch/design_solution_sketch_master_prompt.py
yeagerai/toolkit/load_n_fix_new_tool/__init__.py
yeagerai/toolkit/load_n_fix_new_tool/load_n_fix_new_tool.py
yeagerai/toolkit/load_n_fix_new_tool/load_n_fix_new_tool_master_prompt.py
yeagerai_agent-0.0.41.dist-info/LICENSE
yeagerai_agent-0.0.41.dist-info/METADATA
yeagerai_agent-0.0.41.dist-info/WHEEL
yeagerai_agent-0.0.41.dist-info/entry_points.txt
yeagerai_agent-0.0.41.dist-info/top_level.txt
yeagerai_agent-0.0.41.dist-info/RECORD
