Metadata-Version: 2.1
Name: yeagerai-agent
Version: 0.0.41
Summary: The @yeagerai Agent is used to create your custom LangChain Agents on-the-fly.
Author: YeagerAI LLC
Author-email: jm@yeager.ai
Classifier: Development Status :: 2 - Pre-Alpha
Classifier: Environment :: Web Environment
Classifier: Intended Audience :: Developers
Classifier: License :: OSI Approved :: MIT License
Classifier: Operating System :: OS Independent
Classifier: Programming Language :: Python
Classifier: Programming Language :: Python :: 3
Classifier: Programming Language :: Python :: 3 :: Only
Classifier: Programming Language :: Python :: 3.10
Classifier: Programming Language :: Python :: 3.11
Classifier: Topic :: Software Development :: Libraries :: Application Frameworks
Classifier: Topic :: Software Development :: Libraries :: Python Modules
License-File: LICENSE
Requires-Dist: langchain
Requires-Dist: openai
Requires-Dist: GitPython
Requires-Dist: click
Requires-Dist: gradio
Requires-Dist: python-dotenv
